{
  "@odata.type": "#SoftwareInventory.v1_8_0.SoftwareInventory",
  "Id": "bmc_cpld",
  "Name": "BMC CPLD Firmware",
  "SoftwareId": "cpld",
  "RelatedItem": [
    {
      "@odata.id": "/redfish/v1/Managers/bmc"
    }
  ],
  "RelatedItem@odata.count": 1,
  "Oem": {
    "VersionAfterActivation": "00030E08"
  },
  "Status": {
    "State": "Enabled",
    "HealthRollup": "OK",
    "Health": "OK"
  },
  "Updateable": true,
  "Version": "00030E08",
  "WriteProtected": false,
  "Actions": {
    "Oem": {}
  },
  "@odata.id": "/redfish/v1/UpdateService/FirmwareInventory/bmc_cpld"
}