{
  "@odata.id": "/redfish/v1/Chassis/server2/Sensors/slot2_51",
  "@odata.type": "#Sensor.v1_2_0.Sensor",
  "Id": "51",
  "Name": "slot2/slot2/MB_VR_EHV_CURR_A",
  "Oem": {},
  "PhysicalContext": "Chassis",
  "Reading": 0.800000011920929,
  "ReadingRangeMax": 99999,
  "ReadingRangeMin": -99999,
  "ReadingUnits": "Amps ",
  "Status": {
    "Health": "OK",
    "State": "Enabled"
  },
  "Thresholds": {
    "LowerCaution": {
      "Reading": 0
    },
    "LowerCritical": {
      "Reading": 0
    },
    "LowerFatal": {
      "Reading": 0
    },
    "UpperCaution": {
      "Reading": 5
    },
    "UpperCritical": {
      "Reading": 6
    },
    "UpperFatal": {
      "Reading": 18
    }
  }
}